schwabb/__init__.py
schwabb/_token.py
schwabb/client.py
schwabb/urls.py
schwabb/utils.py
schwabb/websocket.py
schwabb/enums/__init__.py
schwabb/enums/base.py
schwabb/enums/order.py
schwabb/enums/pricehistory.py
schwabb/enums/transaction.py
schwabb/enums/websocket.py
schwabb/models/__init__.py
schwabb/models/accounts.py
schwabb/models/meta.py
schwabb/models/orders.py
schwabb/models/positions.py
schwabb/models/quotes.py
schwabb/models/transactions.py
schwabb/models/userpreferences.py
schwabb/providers/__init__.py
schwabb/providers/abstract.py
schwabb/providers/base.py
schwabb/providers/json.py
schwabb/providers/mysql.py
schwabb/providers/redis.py
schwabb/providers/sqlite.py
my_schwabb-1.0.4.dist-info/LICENSE
my_schwabb-1.0.4.dist-info/METADATA
my_schwabb-1.0.4.dist-info/WHEEL
my_schwabb-1.0.4.dist-info/top_level.txt
my_schwabb-1.0.4.dist-info/RECORD
