Metadata-Version: 2.1
Name: my-schwabb
Version: 1.0.4
Summary: A Python package to interact with the Charles Schwab API.
Author-email: John Gaddis <normlman@live.com>
Classifier: Programming Language :: Python :: 3
Classifier: License :: OSI Approved :: GNU General Public License v3 or later (GPLv3+)
Classifier: Operating System :: OS Independent
Requires-Python: >=3.10
License-File: LICENSE
Requires-Dist: aiohttp[speedups]
Requires-Dist: async-timeout
Requires-Dist: requests
Requires-Dist: orjson
Requires-Dist: pysynchronizer
Requires-Dist: websockets
Provides-Extra: mysql
Requires-Dist: pymysql ; extra == 'mysql'
Provides-Extra: redis
Requires-Dist: redis ; extra == 'redis'
Provides-Extra: websocket
Requires-Dist: websockets ; extra == 'websocket'
